bbm_q/__init__.py
bbm_q/_config.py
bbm_q/api.py
bbm_q/find.py
bbm_q/jupyter.py
bbm_q/tg.py
bbm_q-0.2.3.dist-info/licenses/LICENSE
bbm_q-0.2.3.dist-info/METADATA
bbm_q-0.2.3.dist-info/WHEEL
bbm_q-0.2.3.dist-info/top_level.txt
bbm_q-0.2.3.dist-info/RECORD
