Metadata-Version: 2.4
Name: bbm_q
Version: 0.2.3
Summary: Ultra-minimal.
Author-email: You <you@example.com>
License: MIT
Project-URL: Homepage, https://github.com/yourname/bbm_q
Requires-Python: >=3.8
License-File: LICENSE
Requires-Dist: requests>=2.31
Dynamic: license-file
